feret/.idea/.gitignore
feret/.idea/feret.iml
feret/.idea/inspectionProfiles/profiles_settings.xml
feret/.idea/inspectionProfiles/Project_Default.xml
feret/.idea/misc.xml
feret/.idea/modules.xml
feret/.idea/vcs.xml
feret/10243_binary.tif
feret/104_binary_verrgroessert.tif
feret/11300_binary_verrgroessert.tif
feret/126_binary_verrgroessert.tif
feret/__init__.py
feret/img.npy
feret/main.py
feret/temp.py
feret-1.3.1.dist-info/LICENSE
feret-1.3.1.dist-info/WHEEL
feret-1.3.1.dist-info/METADATA
feret-1.3.1.dist-info/RECORD
