Metadata-Version: 2.1
Name: feret
Version: 1.3.1
Summary: Calculate the maximum and minimum Feret diameter.
Home-page: https://github.com/matthiasnwt/feret
License: MIT
Keywords: feret,feretdiameter,maxferet,diameter,maximum,caliper,caliper diameter,python,minferet,minimum,feret diameter
Author: matthiasnwt
Author-email: 62239991+matthiasnwt@users.noreply.github.com
Requires-Python: >=3,<4
Classifier: Development Status :: 5 - Production/Stable
Classifier: License :: OSI Approved :: MIT License
Classifier: Operating System :: MacOS
Classifier: Operating System :: Microsoft :: Windows
Classifier: Operating System :: Unix
Classifier: Programming Language :: Python
Classifier: Programming Language :: Python :: 3
Classifier: Programming Language :: Python :: 3.10
Classifier: Programming Language :: Python :: 3.4
Classifier: Programming Language :: Python :: 3.5
Classifier: Programming Language :: Python :: 3.6
Classifier: Programming Language :: Python :: 3.7
Classifier: Programming Language :: Python :: 3.8
Classifier: Programming Language :: Python :: 3.9
Classifier: Topic :: Scientific/Engineering
Classifier: Topic :: Scientific/Engineering :: Image Processing
Classifier: Topic :: Scientific/Engineering :: Information Analysis
Classifier: Topic :: Scientific/Engineering :: Physics
Classifier: Topic :: Scientific/Engineering :: Visualization
Classifier: Topic :: Utilities
Requires-Dist: matplotlib (>=3.5.1,<4.0.0)
Requires-Dist: numpy (>=1.22.3,<2.0.0)
Requires-Dist: opencv-python (>=4.5,<5.0)
Requires-Dist: scipy (>=1.8.0,<2.0.0)
Project-URL: Repository, https://github.com/matthiasnwt/feret
